CHANGES.txt
MANIFEST
MANIFEST.in
README.txt
setup.py
ZenPacks/__init__.py
ZenPacks.lbn.Base.egg-info/PKG-INFO
ZenPacks.lbn.Base.egg-info/SOURCES.txt
ZenPacks.lbn.Base.egg-info/dependency_links.txt
ZenPacks.lbn.Base.egg-info/entry_points.txt
ZenPacks.lbn.Base.egg-info/namespace_packages.txt
ZenPacks.lbn.Base.egg-info/not-zip-safe
ZenPacks.lbn.Base.egg-info/requires.txt
ZenPacks.lbn.Base.egg-info/top_level.txt
ZenPacks/lbn/__init__.py
ZenPacks/lbn/Base/__init__.py
ZenPacks/lbn/Base/brand.py
ZenPacks/lbn/Base/config.py
ZenPacks/lbn/Base/configure.zcml
ZenPacks/lbn/Base/setuphandlers.py
ZenPacks/lbn/Base/skins/ZenPacks.lbn.Base/bastion_powered.gif
ZenPacks/lbn/Base/skins/ZenPacks.lbn.Base/bastion_powered.gif.metadata
ZenPacks/lbn/Base/skins/ZenPacks.lbn.Base/logo.png